quillai_filescanner/__init__.py
quillai_filescanner/__main__.py
quillai_filescanner/categories.py
quillai_filescanner/cli.py
quillai_filescanner/config.py
quillai_filescanner/scanner.py
quillai_filescanner/utils.py
quillai_filescanner-1.0.5.dist-info/licenses/LICENSE
quillai_filescanner-1.0.5.dist-info/METADATA
quillai_filescanner-1.0.5.dist-info/WHEEL
quillai_filescanner-1.0.5.dist-info/entry_points.txt
quillai_filescanner-1.0.5.dist-info/top_level.txt
quillai_filescanner-1.0.5.dist-info/RECORD
