Metadata-Version: 2.4
Name: quillai-filescanner
Version: 1.0.5
Summary: A comprehensive file system scanner for organizing and analyzing files
Home-page: https://github.com/quillaiMohammed/filescanner-
Author: Quillai Mohammed Eise Mohammed
Author-email: Quillai Mohammed Eise Mohammed <quillai20011114@gmail.com>
License: MIT
Project-URL: Homepage, https://github.com/quillaiMohammed/filescanner-
Project-URL: Repository, https://github.com/quillaiMohammed/filescanner-
Project-URL: Issues, https://github.com/quillaiMohammed/filescanner-/issues
Keywords: file,scanner,organizer,analyzer,cli
Classifier: Development Status :: 4 - Beta
Classifier: Intended Audience :: Developers
Classifier: Intended Audience :: System Administrators
Classifier: License :: OSI Approved :: MIT License
Classifier: Operating System :: OS Independent
Classifier: Programming Language :: Python :: 3
Classifier: Programming Language :: Python :: 3.7
Classifier: Programming Language :: Python :: 3.8
Classifier: Programming Language :: Python :: 3.9
Classifier: Programming Language :: Python :: 3.10
Classifier: Programming Language :: Python :: 3.11
Requires-Python: >=3.7
License-File: LICENSE
Dynamic: author
Dynamic: home-page
Dynamic: license-file
Dynamic: requires-python
